backend/__init__.py
backend/main.py
backend/api/__init__.py
backend/api/route_baidu.py
backend/api/route_claude.py
backend/api/route_google.py
backend/api/route_minimax.py
backend/api/route_openai.py
backend/api/route_xunfei.py
backend/config/__init__.py
backend/config/biz_config.py
backend/config/constant.py
backend/middleware/ApiKeyDetermineMiddleware.py
backend/middleware/AuthMiddleware.py
backend/middleware/CollectMiddleware.py
backend/middleware/HealthRecordMiddleware.py
backend/middleware/__init__.py
backend/model/__init__.py
backend/model/dto/BaiduDto.py
backend/model/dto/ClaudeDto.py
backend/model/dto/ClaudeSlackDto.py
backend/model/dto/GoogleDto.py
backend/model/dto/MinimaxDto.py
backend/model/dto/OpenaiDto.py
backend/model/dto/ReturnBase.py
backend/model/dto/XunfeiDto.py
backend/model/dto/__init__.py
backend/service/__init__.py
backend/service/service_baidu.py
backend/service/service_claude.py
backend/service/service_google.py
backend/service/service_minimax.py
backend/service/service_openai.py
backend/service/service_redis_key.py
backend/service/service_xunfei.py
backend/util/__init__.py
backend/util/choose_one.py
backend/util/encrypt_util.py
backend/util/env.py
backend/util/example.py
backend/util/exception.py
backend/util/file.py
backend/util/jwt_util.py
backend/util/log.py
backend/util/openai_test.py
backend/util/openai_token_calculate.py
backend/util/rate_limit_util.py
backend/util/rddd.py
backend/util/redis_ops.py
backend/util/request_info.py
backend/util/request_record_util.py
backend/util/run_async.py
backend/util/sealion_notify.py
backend/util/time_util.py
backend/util/uid_rate_limit.py
alles_apin-0.0.1.dist-info/METADATA
alles_apin-0.0.1.dist-info/WHEEL
alles_apin-0.0.1.dist-info/entry_points.txt
alles_apin-0.0.1.dist-info/top_level.txt
alles_apin-0.0.1.dist-info/RECORD
