Metadata-Version: 2.1
Name: alles-apin
Version: 0.0.1
Summary: AOE (All yOu nEed) retrieves answers from different LLM in parallel
Home-page: https://github.com/opensealion/aoe
Author: arkmon
Author-email: 
License: Apache License 2.0
Keywords: alles-apin
Classifier: Development Status :: 3 - Alpha
